jupyterlab_gpulab_theme_dark/__init__.py
jupyterlab_gpulab_theme_dark/_version.py
jupyterlab_gpulab_theme_dark/labextension/build_log.json
jupyterlab_gpulab_theme_dark/labextension/package.json
jupyterlab_gpulab_theme_dark/labextension/static/lib_index_js.247059cfe661dc4c41f7.js
jupyterlab_gpulab_theme_dark/labextension/static/lib_index_js.247059cfe661dc4c41f7.js.map
jupyterlab_gpulab_theme_dark/labextension/static/remoteEntry.ade093184771d5d9a399.js
jupyterlab_gpulab_theme_dark/labextension/static/remoteEntry.ade093184771d5d9a399.js.map
jupyterlab_gpulab_theme_dark/labextension/static/remoteEntry.dd00d06dbe9eca5253d6.js
jupyterlab_gpulab_theme_dark/labextension/static/remoteEntry.dd00d06dbe9eca5253d6.js.map
jupyterlab_gpulab_theme_dark/labextension/static/style.js
jupyterlab_gpulab_theme_dark/labextension/static/style_index_css.33a627dc514da824c5ad.js
jupyterlab_gpulab_theme_dark/labextension/static/style_index_css.33a627dc514da824c5ad.js.map
jupyterlab_gpulab_theme_dark/labextension/static/style_index_css.91b14b143e92e160e624.js
jupyterlab_gpulab_theme_dark/labextension/static/style_index_css.91b14b143e92e160e624.js.map
jupyterlab_gpulab_theme_dark/labextension/static/vendors-node_modules_css-loader_dist_runtime_api_js-node_modules_css-loader_dist_runtime_cssW-926fd9.a492bfa3e03708fbcdf3.js
jupyterlab_gpulab_theme_dark/labextension/static/vendors-node_modules_css-loader_dist_runtime_api_js-node_modules_css-loader_dist_runtime_cssW-926fd9.a492bfa3e03708fbcdf3.js.map
jupyterlab_gpulab_theme_dark/labextension/themes/jupyterlab_gpulab_theme_dark/index.css
jupyterlab_gpulab_theme_dark/labextension/themes/jupyterlab_gpulab_theme_dark/index.js
jupyterlab_gpulab_theme_dark-0.2.0.data/data/share/jupyter/labextensions/jupyterlab_gpulab_theme_dark/build_log.json
jupyterlab_gpulab_theme_dark-0.2.0.data/data/share/jupyter/labextensions/jupyterlab_gpulab_theme_dark/install.json
jupyterlab_gpulab_theme_dark-0.2.0.dist-info/LICENSE
jupyterlab_gpulab_theme_dark-0.2.0.dist-info/METADATA
jupyterlab_gpulab_theme_dark-0.2.0.dist-info/WHEEL
jupyterlab_gpulab_theme_dark-0.2.0.dist-info/top_level.txt
jupyterlab_gpulab_theme_dark-0.2.0.dist-info/RECORD
