Metadata-Version: 2.1
Name: jupyterlab-gpulab-theme-dark
Version: 0.2.0
Summary: GPULab dark theme for JupyterLab
Home-page: https://gitlab.deasilnet.com/gpulab/extensions/jupyterlab-gpulab-theme-dark
Author: GPULab
License: BSD-3-Clause
Keywords: Jupyter,JupyterLab
Platform: Linux
Platform: Mac OS X
Platform: Windows
Classifier: License :: OSI Approved :: BSD License
Classifier: Programming Language :: Python
Classifier: Programming Language :: Python :: 3
Classifier: Programming Language :: Python :: 3.6
Classifier: Programming Language :: Python :: 3.7
Classifier: Programming Language :: Python :: 3.8
Classifier: Framework :: Jupyter
Requires-Python: >=3.6
Requires-Dist: jupyterlab (==3.*,>=3.0.0)
